github_issues_tools/__init__.py
github_issues_tools/github_issues_tools.py
github_issues_tools/metadata.py
github_issues_tools-0.1.0.data/scripts/github-issues-tools
github_issues_tools-0.1.0.dist-info/DESCRIPTION.rst
github_issues_tools-0.1.0.dist-info/METADATA
github_issues_tools-0.1.0.dist-info/RECORD
github_issues_tools-0.1.0.dist-info/WHEEL
github_issues_tools-0.1.0.dist-info/metadata.json
github_issues_tools-0.1.0.dist-info/top_level.txt
